parfam/__init__.py
parfam/benchmark.py
parfam/datasets
parfam/datasets_feynmann
parfam/ngyuen.py
parfam/parfam_torch.py
parfam/parfamwrapper.py
parfam/train.py
parfam/utils.py
parfam/config_files/wrapper/big.ini
parfam/config_files/wrapper/small.ini
parfam/trainingOnSyntheticData/test_dlparfam.py
parfam/trainingOnSyntheticData/train.py
parfam-0.0.1.dist-info/METADATA
parfam-0.0.1.dist-info/WHEEL
parfam-0.0.1.dist-info/top_level.txt
parfam-0.0.1.dist-info/RECORD
