Metadata-Version: 2.4
Name: parfam
Version: 0.0.1
Summary: A symbolic regression package implementing the ParFam algorithm from the ICLR 2025 paper 'ParFam--(Neural Guided) Symbolic Regression via Continuous Global Optimization' (https://openreview.net/pdf?id=8y5Uf6oEiB)
Author-email: Philipp Scholl <philipp.scholl96@web.de>
License-Expression: MIT
Project-URL: GitHub, https://github.com/Philipp238/parfam
Project-URL: Issues, https://github.com/Philipp238/parfam/issues
Project-URL: Paper, https://openreview.net/pdf?id=8y5Uf6oEiB
Classifier: Programming Language :: Python :: 3
Classifier: Operating System :: OS Independent
Requires-Python: >=3.7
